discontinuum/__init__.py
discontinuum/_version.py
discontinuum/data_manager.py
discontinuum/pipeline.py
discontinuum/plot.py
discontinuum/utils.py
discontinuum/engines/__init__.py
discontinuum/engines/base.py
discontinuum/engines/gpytorch.py
discontinuum/engines/pymc.py
discontinuum/providers/__init__.py
discontinuum/providers/base.py
discontinuum/tests/test_pipeline.py
discontinuum-1.0.11.dist-info/licenses/LICENSE.md
loadest_gp/__init__.py
loadest_gp/plot.py
loadest_gp/utils.py
loadest_gp/models/__init__.py
loadest_gp/models/base.py
loadest_gp/models/gpytorch.py
loadest_gp/models/pymc.py
loadest_gp/providers/__init__.py
loadest_gp/providers/usgs.py
rating_gp/pipeline.py
rating_gp/plot.py
rating_gp/models/__init__.py
rating_gp/models/base.py
rating_gp/models/gpytorch.py
rating_gp/models/kernels.py
rating_gp/providers/__init__.py
rating_gp/providers/usgs.py
discontinuum-1.0.11.dist-info/METADATA
discontinuum-1.0.11.dist-info/WHEEL
discontinuum-1.0.11.dist-info/top_level.txt
discontinuum-1.0.11.dist-info/RECORD
