Metadata-Version: 2.4
Name: discontinuum
Version: 1.0.11
Summary: Estimate discontinuous timeseries from continuous covariates.
Maintainer-email: Timothy Hodson <thodson@usgs.gov>
License: License
Project-URL: homepage, https://github.com/thodson-usgs/discontinuum
Project-URL: repository, https://github.com/thodson-usgs/discontinuum.git
Keywords: timeseries,Gaussian processes,discontinuous
Classifier: Programming Language :: Python :: 3
Requires-Python: >=3.9
License-File: LICENSE.md
Requires-Dist: gpytorch
Requires-Dist: matplotlib
Requires-Dist: scikit-learn
Requires-Dist: tqdm
Requires-Dist: xarray
Provides-Extra: dev
Requires-Dist: flake8; extra == "dev"
Requires-Dist: ruff; extra == "dev"
Requires-Dist: pytest-cov[all]; extra == "dev"
Requires-Dist: requests_mock; extra == "dev"
Requires-Dist: dataretrieval; extra == "dev"
Provides-Extra: doc
Requires-Dist: sphinx; extra == "doc"
Requires-Dist: sphinx-book-theme; extra == "doc"
Requires-Dist: myst-nb; extra == "doc"
Requires-Dist: sphinxcontrib-mermaid; extra == "doc"
Requires-Dist: sphinx-copybutton; extra == "doc"
Requires-Dist: ipython; extra == "doc"
Requires-Dist: ipykernel; extra == "doc"
Provides-Extra: gpytorch
Requires-Dist: gpytorch; extra == "gpytorch"
Provides-Extra: pymc
Requires-Dist: pymc>=5.0.0; extra == "pymc"
Provides-Extra: loadest-gp
Requires-Dist: dataretrieval; extra == "loadest-gp"
Provides-Extra: rating-gp
Requires-Dist: dataretrieval; extra == "rating-gp"
Dynamic: license-file
